semantic_copycat_src2id-1.3.1.dist-info/licenses/LICENSE
src2id/__init__.py
src2id/cli/__init__.py
src2id/cli/main.py
src2id/cli/validate.py
src2id/core/__init__.py
src2id/core/cache.py
src2id/core/client.py
src2id/core/config.py
src2id/core/extractor.py
src2id/core/models.py
src2id/core/orchestrator.py
src2id/core/package_identifier.py
src2id/core/purl.py
src2id/core/scanner.py
src2id/core/scorer.py
src2id/core/subcomponent_detector.py
src2id/core/swhid.py
src2id/integrations/__init__.py
src2id/integrations/manifest_parser.py
src2id/integrations/oslili.py
src2id/integrations/upmex.py
src2id/search/__init__.py
src2id/search/hash_search.py
src2id/search/providers.py
src2id/search/strategies.py
src2id/utils/__init__.py
src2id/utils/datetime_utils.py
semantic_copycat_src2id-1.3.1.dist-info/METADATA
semantic_copycat_src2id-1.3.1.dist-info/WHEEL
semantic_copycat_src2id-1.3.1.dist-info/entry_points.txt
semantic_copycat_src2id-1.3.1.dist-info/top_level.txt
semantic_copycat_src2id-1.3.1.dist-info/RECORD
