Metadata-Version: 2.4
Name: semantic-copycat-src2id
Version: 1.3.1
Summary: Source to ID - Identify package coordinates and repositories from source code using multiple strategies
Author-email: "Oscar Valenzuela B." <oscar.valenzuela.b@gmail.com>
License: AGPL-3.0
Project-URL: Homepage, https://github.com/oscarvalenzuelab/semantic-copycat-swh
Project-URL: Bug Tracker, https://github.com/oscarvalenzuelab/semantic-copycat-swh/issues
Project-URL: Source Code, https://github.com/oscarvalenzuelab/semantic-copycat-swh
Classifier: Development Status :: 3 - Alpha
Classifier: Intended Audience :: Developers
Classifier: License :: OSI Approved :: GNU Affero General Public License v3
Classifier: Programming Language :: Python :: 3
Classifier: Programming Language :: Python :: 3.9
Classifier: Programming Language :: Python :: 3.10
Classifier: Programming Language :: Python :: 3.11
Classifier: Programming Language :: Python :: 3.12
Classifier: Topic :: Software Development :: Libraries :: Python Modules
Classifier: Topic :: Software Development :: Version Control
Requires-Python: >=3.9
License-File: LICENSE
Requires-Dist: aiohttp>=3.9.0
Requires-Dist: click>=8.1.0
Requires-Dist: rich>=13.0.0
Requires-Dist: pydantic>=2.0.0
Requires-Dist: tabulate>=0.9.0
Provides-Extra: dev
Requires-Dist: pytest>=7.4.0; extra == "dev"
Requires-Dist: pytest-asyncio>=0.21.0; extra == "dev"
Requires-Dist: pytest-cov>=4.1.0; extra == "dev"
Requires-Dist: pytest-mock>=3.11.0; extra == "dev"
Requires-Dist: black>=23.0.0; extra == "dev"
Requires-Dist: ruff>=0.1.0; extra == "dev"
Requires-Dist: mypy>=1.5.0; extra == "dev"
Requires-Dist: pre-commit>=3.4.0; extra == "dev"
Provides-Extra: swhid
Requires-Dist: miniswhid>=0.1.0; extra == "swhid"
Requires-Dist: swh.model>=6.0.0; extra == "swhid"
Requires-Dist: swh.web>=1.0.0; extra == "swhid"
Provides-Extra: enhanced
Requires-Dist: semantic-copycat-oslili>=1.3.3; extra == "enhanced"
Dynamic: license-file
